setup.py
sw.py
show_color_beta.egg-info/PKG-INFO
show_color_beta.egg-info/SOURCES.txt
show_color_beta.egg-info/dependency_links.txt
show_color_beta.egg-info/top_level.txt