Metadata-Version: 1.0
Name: show-color-beta
Version: 0.2
Summary: depurador de logs servidores de correo
Home-page: https://gitlab.com/sistemasnegros/sw
Author: Kevin Franco
Author-email: sistemasnegros@gmail.com
License: GPL
Platform: UNKNOWN
